chebifier/__init__.py
chebifier/__main__.py
chebifier/check_env.py
chebifier/cli.py
chebifier/ensemble.yml
chebifier/hugging_face.py
chebifier/inconsistency_resolution.py
chebifier/model_registry.py
chebifier/model_registry.yml
chebifier/utils.py
chebifier/ensemble/__init__.py
chebifier/ensemble/base_ensemble.py
chebifier/ensemble/weighted_majority_ensemble.py
chebifier/prediction_models/__init__.py
chebifier/prediction_models/base_predictor.py
chebifier/prediction_models/c3p_predictor.py
chebifier/prediction_models/chebi_lookup.py
chebifier/prediction_models/chemlog_predictor.py
chebifier/prediction_models/electra_predictor.py
chebifier/prediction_models/gnn_predictor.py
chebifier/prediction_models/nn_predictor.py
chebifier-1.1.1.dist-info/licenses/LICENSE
chebifier-1.1.1.dist-info/METADATA
chebifier-1.1.1.dist-info/WHEEL
chebifier-1.1.1.dist-info/top_level.txt
chebifier-1.1.1.dist-info/RECORD
