Metadata-Version: 2.4
Name: chebifier
Version: 1.1.1
Summary: An AI ensemble model for predicting chemical classes
Author-email: Simon Flügel <simon.fluegel@uni-osnabrueck.de>
License:                     GNU GENERAL PUBLIC LICENSE
Classifier: Programming Language :: Python :: 3
Classifier: License :: OSI Approved :: GNU General Public License v3 (GPLv3)
Classifier: Operating System :: OS Independent
Requires-Python: >=3.9
License-File: LICENSE
Requires-Dist: click
Requires-Dist: pyyaml
Requires-Dist: torch
Requires-Dist: tqdm
Requires-Dist: rdkit
Requires-Dist: chebai>=1.0.1
Requires-Dist: chemlog>=1.0.4
Requires-Dist: c3p
Provides-Extra: dev
Requires-Dist: black; extra == "dev"
Requires-Dist: isort; extra == "dev"
Requires-Dist: pre-commit; extra == "dev"
Dynamic: license-file
